jaxls/__init__.py
jaxls/__main__.py
jaxls/methods.py
jaxls/typed.py
jaxls-2024.0.1.dist-info/METADATA
jaxls-2024.0.1.dist-info/WHEEL
jaxls-2024.0.1.dist-info/entry_points.txt
jaxls-2024.0.1.dist-info/top_level.txt
jaxls-2024.0.1.dist-info/RECORD
