Metadata-Version: 2.1
Name: jaxls
Version: 2024.0.1
Summary: JAX Language Server APIs.
Author-email: epiqueras <19157096+epiqueras@users.noreply.github.com>
License: UNLICENSED
Project-URL: Homepage, https://github.com/epiqueras/jaxls
Project-URL: Repository, https://github.com/epiqueras/jaxls.git
Requires-Python: >=3.10
Requires-Dist: jax>=0.4.35
Requires-Dist: typer
Requires-Dist: pydantic
Requires-Dist: absl-py
